swaggergroq/__init__.py
swaggergroq/generate_data.py
swaggerwithgroq-0.1.0.dist-info/METADATA
swaggerwithgroq-0.1.0.dist-info/WHEEL
swaggerwithgroq-0.1.0.dist-info/top_level.txt
swaggerwithgroq-0.1.0.dist-info/RECORD
