Metadata-Version: 2.1
Name: swaggerwithgroq
Version: 0.1.0
Summary: Generate realistic API data from Swagger json using Groq
Home-page: https://github.com/TowsifAhamed/swaggerwithgroq/
Author: Towsif Ahamed Labib
Author-email: towsif.kuet.ac.bd@gmail.com
License: UNKNOWN
Platform: UNKNOWN
Classifier: Programming Language :: Python :: 3
Classifier: License :: OSI Approved :: MIT License
Requires-Dist: groq
Requires-Dist: pyyaml
Requires-Dist: requests
